sinol_make/__init__.py
sinol_make/util.py
sinol_make/commands/chkwer/__init__.py
sinol_make/commands/chkwer/chkwer_util.py
sinol_make/commands/doc/__init__.py
sinol_make/commands/export/__init__.py
sinol_make/commands/gen/__init__.py
sinol_make/commands/ingen/__init__.py
sinol_make/commands/ingen/ingen_util.py
sinol_make/commands/init/__init__.py
sinol_make/commands/inwer/__init__.py
sinol_make/commands/inwer/inwer_util.py
sinol_make/commands/outgen/__init__.py
sinol_make/commands/outgen/outgen_util.py
sinol_make/commands/run/__init__.py
sinol_make/commands/verify/__init__.py
sinol_make/contest_types/__init__.py
sinol_make/contest_types/default.py
sinol_make/contest_types/icpc.py
sinol_make/contest_types/oi.py
sinol_make/contest_types/oij.py
sinol_make/contest_types/talent.py
sinol_make/executors/__init__.py
sinol_make/executors/detailed.py
sinol_make/executors/sio2jail.py
sinol_make/executors/time.py
sinol_make/helpers/__init__.py
sinol_make/helpers/cache.py
sinol_make/helpers/classinit.py
sinol_make/helpers/compile.py
sinol_make/helpers/compiler.py
sinol_make/helpers/func_cache.py
sinol_make/helpers/oicompare.py
sinol_make/helpers/package_util.py
sinol_make/helpers/parsers.py
sinol_make/helpers/paths.py
sinol_make/helpers/printer.py
sinol_make/interfaces/BaseCommand.py
sinol_make/interfaces/Errors.py
sinol_make/interfaces/__init__.py
sinol_make/sio2jail/__init__.py
sinol_make/sio2jail/perf_test.py
sinol_make/structs/__init__.py
sinol_make/structs/cache_structs.py
sinol_make/structs/chkwer_structs.py
sinol_make/structs/compiler_structs.py
sinol_make/structs/gen_structs.py
sinol_make/structs/inwer_structs.py
sinol_make/structs/run_structs.py
sinol_make/structs/status_structs.py
sinol_make/task_type/__init__.py
sinol_make/task_type/interactive.py
sinol_make/task_type/normal.py
st_make-1.0.0.dist-info/licenses/LICENSE
st_make-1.0.0.dist-info/METADATA
st_make-1.0.0.dist-info/WHEEL
st_make-1.0.0.dist-info/entry_points.txt
st_make-1.0.0.dist-info/top_level.txt
st_make-1.0.0.dist-info/RECORD
