Metadata-Version: 2.4
Name: st_make
Version: 1.0.0
Summary: CLI tool for creating sio2 task packages [Forked from sio2project/sinol-make]
Author: Stanisław Czech
Author-email: sczech@adespawn.pl
Maintainer: Stanisław Czech, Olaf Targowski
Maintainer-email: sczech@adespawn.pl, me@otsrv.net
Project-URL: Bug Tracker, https://github.com/Stowarzyszenie-Talent/st-make/issues
Project-URL: Homepage, https://github.com/Stowarzyszenie-Talent/st-make
Classifier: Programming Language :: Python :: 3
Classifier: License :: OSI Approved :: GNU General Public License v3 (GPLv3)
Classifier: Operating System :: OS Independent
Requires-Python: >=3.9
License-File: LICENSE
Requires-Dist: argparse
Requires-Dist: argcomplete
Requires-Dist: requests
Requires-Dist: PyYAML
Requires-Dist: dictdiffer
Requires-Dist: importlib-resources
Requires-Dist: psutil
Requires-Dist: packaging
Provides-Extra: tests
Requires-Dist: pytest; extra == "tests"
Requires-Dist: pytest-cov; extra == "tests"
Requires-Dist: pytest-xdist; extra == "tests"
Requires-Dist: requests-mock; extra == "tests"
Dynamic: license-file
